{
  "id": "c66ee24e-9ac0-4803-a659-5f11f102d936",
  "original_path": "/data/SWATGenXApp/Users/admin/Reports/20250412_172208/snodas/snodas_report.md",
  "filename": "snodas_report.md",
  "added_time": "2025-04-15T08:40:40.672132",
  "metadata": {
    "file_type_tag": "markdown"
  },
  "content": "This is a comprehensive report on snowpack and hydrological trends in a specific region, using data from the Snow Data Assimilation System (SNODAS). The report provides an overview of the dataset, methodology, and key findings. Here's a summary:\n\n**Key Findings:**\n\n1. **Significant decrease in snow water equivalent**: A decreasing trend in SWE over the analyzed period.\n2. **Increase in snowmelt rates**: A significant increase in snowmelt rates, with potential impacts on peak flows, flood risk, and aquatic ecosystems.\n3. **Snowpack contribution to annual water budget**: The region has substantial snow water storage, making snowmelt a critical component of the annual water budget.\n\n**Applications and Recommendations:**\n\n1. **Water management applications**: Adjust reservoir operations, flood forecasting, drought planning, and water allocation based on SWE and melt rate data.\n2. **Hydrological applications**: Use SWE data to predict spring and summer runoff volumes, manage for environmental flows, and assess climate change impacts.\n\n**Limitations:**\n\n1. **Temporal range and resolution**: The analysis is limited by the availability of data.\n2. **Uncertainty in SNODAS data**: The dataset combines model and observational data, introducing some uncertainty.\n3. **Spatial resolution**: The spatial resolution may not capture fine-scale variability in complex terrain.\n\n**Data Export:**\n\nThe complete dataset has been exported to CSV format and is available for access.\n\nOverall, this report provides valuable insights into snowpack trends and their implications for water resources in the region. It highlights the need for continued monitoring and management of these critical components of the hydrological cycle.",
  "context": {
    "raw_content": "# SNODAS Snow Data Analysis Report\n\n## Overview\n\n**Period:** 2015 to 2020\n\n**Temporal Resolution:** monthly\n\n**Region:** Lat [44.0315, 44.6131], Lon [-85.1355, -84.2785]\n\n**Available Variables:**\n\n- Snowmelt Rate (mm)\n- Snow Accumulation (mm)\n- Snow Layer Thickness (mm)\n- Snow Water Equivalent (mm)\n- Snowpack Sublimation Rate (mm)\n\n## Summary Statistics\n\n### Snowmelt Rate\n\n**Mean:** 12961.19 mm\n\n**Minimum:** 417.11 mm\n\n**Maximum:** 17216.47 mm\n\n**Standard Deviation:** 5982.43 mm\n\n**Trend Analysi"
  },
  "memory_path": "/data/SWATGenXApp/codes/assistant/memory/files/c66ee24e-9ac0-4803-a659-5f11f102d936",
  "file_extension": ".md",
  "file_type": "text",
  "keywords": [
    "this",
    "aquatic",
    "layer",
    "recommendations",
    "statistics",
    "format",
    "data",
    "markdown",
    "continued",
    "comprehensive",
    "spatial",
    "risk",
    "complex",
    "applications",
    "access",
    "terrain",
    "export",
    "dataset",
    "climate",
    "highlights",
    "snowpack",
    "analysi",
    "csv",
    "flood",
    "predict",
    "5982",
    "12961",
    "resolution",
    "analysis",
    "combines",
    "assess",
    "availability",
    "region",
    "snow",
    "budget",
    "snowmelt",
    "over",
    "rates",
    "management",
    "rate",
    "provides",
    "range",
    "maximum",
    "417",
    "limitations",
    "potential",
    "6131",
    "specific",
    "standard",
    "flows",
    "methodology",
    "been",
    "mean",
    "summary",
    "available",
    "environmental",
    "resources",
    "2015",
    "change",
    "need",
    "insights",
    "minimum",
    "into",
    "component",
    "2020",
    "variability",
    "17216",
    "complete",
    "temporal",
    "volumes",
    "manage",
    "significant",
    "observational",
    "storage",
    "decrease",
    "based",
    "annual",
    "melt",
    "using",
    "uncertainty",
    "key",
    "adjust",
    "decreasing",
    "critical",
    "capture",
    "cycle",
    "trends",
    "swe",
    "has",
    "impacts",
    "snodas",
    "model",
    "introducing",
    "not",
    "monthly",
    "increase",
    "spring",
    "sublimation",
    "lon",
    "hydrological",
    "exported",
    "0315",
    "some",
    "2785",
    "runoff",
    "making",
    "planning",
    "substantial",
    "lat",
    "components",
    "contribution",
    "peak",
    "snodas_report",
    "drought",
    "1355",
    "period",
    "equivalent",
    "water",
    "reservoir",
    "overview",
    "use",
    "allocation",
    "system",
    "accumulation",
    "thickness",
    "forecasting",
    "report",
    "summer",
    "fine",
    "ecosystems",
    "may",
    "trend",
    "these",
    "their",
    "valuable",
    "operations",
    "variables",
    "limited",
    "raw_content",
    "assimilation",
    "overall",
    "findings",
    "scale",
    "monitoring",
    "here",
    "implications",
    "deviation",
    "analyzed"
  ]
}