{
  "id": "ee24dea4-395f-44ee-b91b-0432114f013c",
  "original_path": "/data/SWATGenXApp/Users/admin/Reports/20250412_172208/climate_change/climate_change_report.md",
  "filename": "climate_change_report.md",
  "added_time": "2025-04-15T10:51:11.774764",
  "metadata": {
    "file_type_tag": "markdown"
  },
  "content": "This report provides a comprehensive analysis of projected climate change impacts in a specific region, based on downscaled climate projections from the LOCA2 dataset. The report covers various aspects of climate change, including temperature and precipitation changes, their implications for agriculture and water resources, and recommendations for adaptation measures.\n\n**Key Findings:**\n\n1.  **Temperature Increase:** A projected warming of approximately 2.9\u00b0C in mean temperature.\n2.  **Precipitation Changes:** Minimal changes in overall precipitation amounts, but changes in timing, intensity, and seasonal distribution may still have significant agricultural impacts.\n3.  **Emission Scenario Impact:** Higher emission scenarios consistently show more pronounced climate changes, particularly for temperature increases.\n4.  **Temporal Progression:** Climate changes generally intensify over time, with the most significant changes observed in the late-century period (2075-2100).\n5.  **Spatial Variability:** Some regions within the study area show greater sensitivity to climate change, with notable 'hot spots' of temperature increase or precipitation change.\n\n**Adaptation Recommendations:**\n\n1.  **Agricultural Adaptations:**\n    *   Evaluate and adjust crop selection and varieties for future climate conditions\n    *   Review and optimize planting calendars to align with shifting seasonal patterns\n    *   Invest in irrigation infrastructure and water-efficient technologies\n    *   Implement soil conservation practices to enhance resilience to both wet and dry extremes\n    *   Diversify farming systems to reduce climate-related risks\n2.  **Water Resource Management:**\n    *   Evaluate water storage and distribution systems for changing precipitation patterns\n    *   Update flood and drought management plans based on projected changes\n    *   Implement watershed management practices that enhance resilience to climate extremes\n    *   Consider water allocation strategies that account for changing water availability\n\n**Methodology:**\n\nThe report uses the LOCA2 dataset, which provides downscaled climate projections. The analysis includes:\n\n1.  **Data Extraction:** Historical and future scenario data from LOCA2 datasets.\n2.  **Calculation of Climate Change Metrics:** Spatial means and temporal aggregation, calculation of absolute and percentage changes in temperature and precipitation.\n3.  **Visualization:** Time series, spatial patterns, and seasonal cycles are visualized to communicate the findings.\n4.  **Multi-Scenario Analysis:** The analysis is conducted across different time periods and emissions pathways to provide a comprehensive understanding of climate change impacts.\n\n**Conclusion:**\n\nClimate change will bring significant changes to temperature and precipitation patterns in the study region. Adaptation strategies in agriculture, water management, and related sectors are crucial for mitigating these impacts. The report highlights the importance of continued monitoring and periodic updates to this analysis as climate science and projections evolve.",
  "context": {
    "raw_content": "# Climate Change Analysis Report\n\n## Introduction\n\nThis report presents an analysis of projected climate change based on LOCA2 (Localized Constructed Analog) climate model data. It compares historical climate conditions with future scenarios to identify key changes in temperature and precipitation patterns.\n\n## Data Sources\n\n### Historical Data\n\n- **Climate Model**: ACCESS-CM2\n- **Ensemble**: r1i1p1f1\n- **Time Period**: 2000 to 2014\n- **Temporal Resolution**: monthly\n\n### Future Scenarios\n\n#### "
  },
  "memory_path": "/data/SWATGenXApp/codes/assistant/memory/files/ee24dea4-395f-44ee-b91b-0432114f013c",
  "file_extension": ".md",
  "file_type": "text",
  "keywords": [
    "show",
    "mean",
    "conditions",
    "this",
    "hot",
    "mitigating",
    "projected",
    "datasets",
    "identify",
    "which",
    "distribution",
    "resources",
    "increase",
    "warming",
    "comprehensive",
    "spatial",
    "calculation",
    "will",
    "key",
    "climate_change_report",
    "projections",
    "infrastructure",
    "extremes",
    "variability",
    "watershed",
    "highlights",
    "update",
    "extraction",
    "pathways",
    "resource",
    "science",
    "temporal",
    "may",
    "specific",
    "crop",
    "practices",
    "including",
    "sectors",
    "reduce",
    "data",
    "provides",
    "compares",
    "higher",
    "calendars",
    "sources",
    "adaptations",
    "recommendations",
    "findings",
    "efficient",
    "region",
    "consistently",
    "loca2",
    "irrigation",
    "intensify",
    "agriculture",
    "approximately",
    "report",
    "conducted",
    "strategies",
    "observed",
    "diversify",
    "provide",
    "dataset",
    "metrics",
    "ensemble",
    "resolution",
    "notable",
    "uses",
    "changing",
    "raw_content",
    "downscaled",
    "implications",
    "impact",
    "shifting",
    "aspects",
    "varieties",
    "different",
    "various",
    "updates",
    "resilience",
    "most",
    "progression",
    "wet",
    "changes",
    "particularly",
    "scenario",
    "greater",
    "systems",
    "related",
    "pronounced",
    "minimal",
    "2100",
    "implement",
    "impacts",
    "over",
    "future",
    "based",
    "monthly",
    "understanding",
    "have",
    "crucial",
    "presents",
    "absolute",
    "overall",
    "evaluate",
    "localized",
    "model",
    "seasonal",
    "time",
    "regions",
    "farming",
    "drought",
    "availability",
    "bring",
    "cycles",
    "plans",
    "2000",
    "enhance",
    "visualization",
    "markdown",
    "analysis",
    "scenarios",
    "nthis",
    "their",
    "introduction",
    "covers",
    "allocation",
    "across",
    "monitoring",
    "access",
    "aggregation",
    "evolve",
    "study",
    "periods",
    "analog",
    "measures",
    "optimize",
    "precipitation",
    "within",
    "conservation",
    "temperature",
    "periodic",
    "cm2",
    "soil",
    "agricultural",
    "2075",
    "late",
    "still",
    "flood",
    "that",
    "means",
    "visualized",
    "selection",
    "review",
    "management",
    "includes",
    "intensity",
    "communicate",
    "water",
    "sensitivity",
    "invest",
    "spots",
    "continued",
    "account",
    "emission",
    "climate",
    "2014",
    "significant",
    "area",
    "century",
    "adjust",
    "timing",
    "increases",
    "methodology",
    "some",
    "importance",
    "these",
    "multi",
    "planting",
    "adaptation",
    "historical",
    "constructed",
    "period",
    "series",
    "emissions",
    "more",
    "change",
    "percentage",
    "consider",
    "generally",
    "technologies",
    "risks",
    "both",
    "conclusion",
    "align",
    "amounts",
    "dry",
    "r1i1p1f1",
    "storage",
    "patterns"
  ]
}