{
  "id": "6de92f25-b5ec-4168-a1a4-2added393774",
  "original_path": "/data/SWATGenXApp/Users/admin/Reports/20250412_172208/nsrdb/nsrdb_report.md",
  "filename": "nsrdb_report.md",
  "added_time": "2025-04-15T12:27:57.784797",
  "metadata": {
    "file_type_tag": "markdown"
  },
  "content": "This is a comprehensive report on solar radiation and related climate variables using the National Solar Radiation Database (NSRDB). The report provides an in-depth analysis of various aspects, including:\n\n1. **Solar Energy Potential**: The report assesses the solar energy potential of the region, providing insights into the feasibility of solar installations.\n2. **Photovoltaic System Design**: The analysis helps design and optimize photovoltaic systems for optimal performance.\n3. **Solar Resource Forecasting**: The report provides data on short-term and long-term solar radiation forecasting, enabling better decision-making.\n4. **Agricultural Applications**: The NSRDB data can inform agricultural decisions related to evapotranspiration modeling, crop growth modeling, and irrigation scheduling.\n\nThe report also covers:\n\n1. **Time Series Analysis**: A time series analysis of the climate variables over the entire period is presented.\n2. **Spatial Distribution**: Spatial maps show the distribution of climate variables across the study area.\n3. **Climate Variable Correlations**: The analysis examines correlations between solar radiation and other climate variables, including humidity, wind speed, and aridity index.\n\n**Methodology**\n\nThe report uses a combination of satellite imagery, ground measurements, and physical models to generate gridded estimates of solar radiation and related variables. The processing steps include:\n\n1. Data extraction from HDF5 database\n2. Scaling factors application\n3. Spatial subsetting\n4. Temporal aggregation\n5. Statistical analysis and visualization\n\n**Limitations**\n\nThe report acknowledges limitations in data accuracy due to cloud cover, atmospheric conditions, and spatial resolution.\n\n**Data Export**\n\nThe complete dataset is exported to CSV format for further use.\n\nOverall, this comprehensive report provides valuable insights into solar radiation and related climate variables, enabling informed decision-making for various applications.",
  "context": {
    "raw_content": "# NSRDB Climate Data Analysis Report\n\n## Overview\n\n**Period:** 2015 to 2020\n\n**Data Source:** National Solar Radiation Database (NSRDB)\n\n**Region:** Lat [44.0315, 44.6131], Lon [-85.1355, -84.2785]\n\n**Available Variables:**\n\n- Global Horizontal Irradiance (W/m\u00b2)\n- Wind Speed (m/s)\n- Relative Humidity (%)\n\n## Summary Statistics\n\n### Global Horizontal Irradiance\n\n**Mean:** 159.05 W/m\u00b2\n\n**Minimum:** 10.30 W/m\u00b2\n\n**Maximum:** 376.30 W/m\u00b2\n\n**Standard Deviation:** 98.53 W/m\u00b2\n\n**Temporal Variability:** "
  },
  "memory_path": "/data/SWATGenXApp/codes/assistant/memory/files/6de92f25-b5ec-4168-a1a4-2added393774",
  "file_extension": ".md",
  "file_type": "text",
  "keywords": [
    "nsrdb",
    "accuracy",
    "6131",
    "limitations",
    "can",
    "2785",
    "period",
    "index",
    "extraction",
    "models",
    "series",
    "further",
    "various",
    "informed",
    "correlations",
    "statistical",
    "valuable",
    "optimize",
    "raw_content",
    "available",
    "across",
    "nsrdb_report",
    "maximum",
    "format",
    "ground",
    "generate",
    "subsetting",
    "related",
    "scaling",
    "2020",
    "providing",
    "lat",
    "inform",
    "this",
    "making",
    "data",
    "use",
    "study",
    "including",
    "over",
    "overall",
    "statistics",
    "also",
    "relative",
    "feasibility",
    "speed",
    "include",
    "system",
    "satellite",
    "cover",
    "mean",
    "using",
    "hdf5",
    "between",
    "0315",
    "growth",
    "variable",
    "export",
    "term",
    "examines",
    "area",
    "irrigation",
    "agricultural",
    "estimates",
    "cloud",
    "wind",
    "resource",
    "maps",
    "atmospheric",
    "time",
    "aggregation",
    "decisions",
    "due",
    "variability",
    "2015",
    "spatial",
    "exported",
    "measurements",
    "entire",
    "standard",
    "lon",
    "into",
    "better",
    "376",
    "comprehensive",
    "crop",
    "national",
    "imagery",
    "source",
    "covers",
    "performance",
    "markdown",
    "visualization",
    "resolution",
    "photovoltaic",
    "physical",
    "combination",
    "gridded",
    "1355",
    "summary",
    "global",
    "show",
    "energy",
    "enabling",
    "irradiance",
    "processing",
    "decision",
    "temporal",
    "factors",
    "acknowledges",
    "provides",
    "159",
    "other",
    "variables",
    "modeling",
    "dataset",
    "deviation",
    "depth",
    "radiation",
    "minimum",
    "aspects",
    "analysis",
    "steps",
    "presented",
    "complete",
    "region",
    "solar",
    "helps",
    "assesses",
    "climate",
    "long",
    "optimal",
    "database",
    "humidity",
    "installations",
    "systems",
    "overview",
    "potential",
    "forecasting",
    "short",
    "report",
    "aridity",
    "distribution",
    "csv",
    "applications",
    "conditions",
    "application",
    "scheduling",
    "insights",
    "design",
    "horizontal",
    "methodology",
    "evapotranspiration",
    "uses"
  ]
}