{
  "session_id": "20250414_212341",
  "interaction_id": "20250414_212341_16",
  "timestamp": "2025-04-14T21:24:42.006855",
  "query": "Analyze MOD13Q1_EVI_stats.csv",
  "response": "The provided CSV file contains summary statistics for the Enhanced Vegetation Index (EVI) data from MODIS (Moderate Resolution Imaging Spectroradiometer) satellite imagery.\n\nHere's a brief summary of the key points:\n\n1. **Data**: The EVI values range from -0.199 to 0.8913, with an average value of 0.2787.\n2. **Distribution**:\n\t* Mean: 0.2787\n\t* Standard Deviation (StdDev): 0.1290\n\t* Minimum (Min): -0.0887\n\t* Maximum (Max): 0.6360\n3. **Yearly and Monthly Distribution**:\n\t* Year: The data spans from 2015 to 2018, with an average year of 2016.\n\t* Month: The data spans from January (1) to December (12), with an average month of June (6).\n4. **Key Statistics**: The provided JSON object contains the mean, min, max, and standard deviation values for each statistic.\n\nSome interesting observations:\n\n* The EVI values are generally positive, indicating healthy vegetation.\n* The highest EVI value is 0.8913, while the lowest value is -0.199.\n* The data spans three years (2015-2018), with an average year of 2016.\n* The distribution of EVI values is relatively narrow, with a standard deviation of around 0.13.\n\nOverall, this summary provides an overview of the statistical properties of the MODIS EVI data, which can be useful for further analysis or interpretation.",
  "query_info": {
    "original_query": "analyse MOD13Q1_EVI_stats.csv",
    "keywords": [
      "mod13q1_evi_stats",
      "csv",
      ".c"
    ],
    "length": 29,
    "intent": "analyze",
    "entities": [],
    "file_references": [
      "MOD13Q1_EVI_stats.csv"
    ]
  },
  "files_accessed": [
    "/data/SWATGenXApp/Users/admin/Reports/20250324_222749/modis/comprehensive/MOD13Q1_EVI/MOD13Q1_EVI_stats.csv"
  ]
}